grand_cypher_io/__init__.py
grand_cypher_io/test_io.py
grand_cypher_io/test_utils.py
grand_cypher_io-0.1.0.dist-info/LICENSE
grand_cypher_io-0.1.0.dist-info/METADATA
grand_cypher_io-0.1.0.dist-info/WHEEL
grand_cypher_io-0.1.0.dist-info/RECORD
