Metadata-Version: 2.1
Name: grand-cypher-io
Version: 0.1.0
Summary: File IO routines for reading and writing OpenCypher files
License: Apache 2.0
Author: Jordan Matelsky
Author-email: opensource@matelsky.com
Requires-Python: >=3.10,<3.13
Classifier: License :: Other/Proprietary License
Classifier: Programming Language :: Python :: 3
Classifier: Programming Language :: Python :: 3.10
Classifier: Programming Language :: Python :: 3.11
Requires-Dist: dask (>=2023.9.3,<2024.0.0)
Requires-Dist: networkx (>=3.1,<4.0)
Requires-Dist: numpy (>=1.26.0,<2.0.0)
